pfagd/__init__.py
pfagd/version.py
pfagd/assets/__init__.py
pfagd/assets/manager.py
pfagd/cli/__init__.py
pfagd/cli/build.py
pfagd/cli/main.py
pfagd/cli/monetization.py
pfagd/cli/scaffold.py
pfagd/engine/__init__.py
pfagd/engine/core.py
pfagd/engine/renderer.py
pfagd/examples/demo_game/README.md
pfagd/examples/demo_game/main.py
pfagd/examples/demo_game/assets/README.md
pfagd/ui/__init__.py
pfagd/ui/widgets.py
pfagd-0.1.0.dist-info/licenses/LICENSE
pfagd-0.1.0.dist-info/METADATA
pfagd-0.1.0.dist-info/WHEEL
pfagd-0.1.0.dist-info/entry_points.txt
pfagd-0.1.0.dist-info/top_level.txt
pfagd-0.1.0.dist-info/RECORD
