Metadata-Version: 2.4
Name: pfagd
Version: 0.1.0
Summary: Python for Android Game Development - Cross-platform game framework
Home-page: https://github.com/pfagd/pfagd
Author: PFAGD Development Team
Author-email: PFAGD Development Team <dev@pfagd.org>
License: MIT
Project-URL: Homepage, https://github.com/pfagd/pfagd
Project-URL: Documentation, https://pfagd.readthedocs.io/
Project-URL: Repository, https://github.com/pfagd/pfagd
Project-URL: Bug Tracker, https://github.com/pfagd/pfagd/issues
Project-URL: Changelog, https://github.com/pfagd/pfagd/blob/main/CHANGELOG.md
Keywords: game,development,android,cross-platform,kivy,mobile,desktop,2d,3d,gamedev
Classifier: Development Status :: 3 - Alpha
Classifier: Intended Audience :: Developers
Classifier: Topic :: Games/Entertainment
Classifier: Topic :: Software Development :: Libraries :: Python Modules
Classifier: Topic :: Multimedia :: Graphics
Classifier: Topic :: Multimedia :: Sound/Audio
Classifier: License :: OSI Approved :: MIT License
Classifier: Operating System :: OS Independent
Classifier: Programming Language :: Python :: 3
Classifier: Programming Language :: Python :: 3.8
Classifier: Programming Language :: Python :: 3.9
Classifier: Programming Language :: Python :: 3.10
Classifier: Programming Language :: Python :: 3.11
Classifier: Programming Language :: Python :: 3.12
Requires-Python: >=3.8
License-File: LICENSE
Requires-Dist: kivy>=2.1.0
Requires-Dist: Pillow>=8.0.0
Requires-Dist: requests>=2.25.0
Requires-Dist: buildozer>=1.4.0
Requires-Dist: PyInstaller>=4.0
Provides-Extra: android
Requires-Dist: pyjnius>=1.4.0; extra == "android"
Requires-Dist: plyer>=2.0.0; extra == "android"
Provides-Extra: desktop
Requires-Dist: pygame>=2.0.0; extra == "desktop"
Requires-Dist: PyQt5>=5.15.0; extra == "desktop"
Provides-Extra: dev
Requires-Dist: pytest>=6.0.0; extra == "dev"
Requires-Dist: pytest-cov>=2.0.0; extra == "dev"
Requires-Dist: black>=21.0.0; extra == "dev"
Requires-Dist: flake8>=3.8.0; extra == "dev"
Requires-Dist: mypy>=0.800; extra == "dev"
Requires-Dist: sphinx>=4.0.0; extra == "dev"
Requires-Dist: sphinx-rtd-theme>=1.0.0; extra == "dev"
Provides-Extra: all
Requires-Dist: pyjnius>=1.4.0; extra == "all"
Requires-Dist: plyer>=2.0.0; extra == "all"
Requires-Dist: pygame>=2.0.0; extra == "all"
Requires-Dist: PyQt5>=5.15.0; extra == "all"
Requires-Dist: pytest>=6.0.0; extra == "all"
Requires-Dist: pytest-cov>=2.0.0; extra == "all"
Requires-Dist: black>=21.0.0; extra == "all"
Requires-Dist: flake8>=3.8.0; extra == "all"
Requires-Dist: mypy>=0.800; extra == "all"
Requires-Dist: sphinx>=4.0.0; extra == "all"
Requires-Dist: sphinx-rtd-theme>=1.0.0; extra == "all"
Dynamic: author
Dynamic: home-page
Dynamic: license-file
Dynamic: requires-python
